setup.py
dsnd_probability_nj/Binomialdistribution.py
dsnd_probability_nj/Gaussiandistribution.py
dsnd_probability_nj/Generaldistribution.py
dsnd_probability_nj/__init__.py
dsnd_probability_nj.egg-info/PKG-INFO
dsnd_probability_nj.egg-info/SOURCES.txt
dsnd_probability_nj.egg-info/dependency_links.txt
dsnd_probability_nj.egg-info/not-zip-safe
dsnd_probability_nj.egg-info/top_level.txt