Metadata-Version: 1.0
Name: dsnd-probability-nj
Version: 1.1
Summary: Gaussian and Binomial distributions
Home-page: UNKNOWN
Author: Nirav Jain
Author-email: jainnirav125@gmail.com
License: UNKNOWN
Platform: UNKNOWN
